{
  "uuid": "1936be1e-fc2f-4896-a06b-62c1956fb572",
  "display_id": 2,
  "title": "Push and create PR for kickoff CI verification feature",
  "status": "closed",
  "priority": "low",
  "created_by": "m1--f1",
  "created_at": "2026-02-27T04:20:36.051540Z",
  "updated_at": "2026-03-02T09:44:11.126240Z",
  "closed_at": "2026-03-02T09:44:11.126240Z",
  "labels": [
    "feature"
  ],
  "comments": [
    {
      "id": 170,
      "author": "maxine-at-forecast--noether--ratatui-tui",
      "content": "Result: Switched to Viewport::Inline(14), clears viewport area after walkthrough. Reordered run() so TUI happens before any fs::create_dir_all/fs::write — Esc exits cleanly. 146 tests pass, clippy/fmt clean.",
      "created_at": "2026-03-02T09:44:09.512029Z",
      "kind": "result"
    }
  ]
}